applechess/__init__.py
applechess/chess_agent.py
applechess/lichess_bot.py
applechess-0.1.dist-info/LICENSE
applechess-0.1.dist-info/METADATA
applechess-0.1.dist-info/WHEEL
applechess-0.1.dist-info/top_level.txt
applechess-0.1.dist-info/RECORD
