Metadata-Version: 2.1
Name: applechess
Version: 0.1
Summary: A simple alpha-beta chess engine with a Lichess bot interface.
Author-email: Levin Ma <llmar1000000@gmail.com>
Project-URL: Homepage, https://github.com/appleplectic/applechess
Project-URL: Documentation, https://appleplectic.github.io/applechess/
Project-URL: Repository, https://github.com/appleplectic/applechess.git
Project-URL: Issues, https://github.com/appleplectic/applechess/issues
Keywords: chess,engine,alpha,beta,minimax,applechess,apple,pruning
Classifier: License :: OSI Approved :: GNU General Public License v3 (GPLv3)
Classifier: Development Status :: 3 - Alpha
Classifier: Intended Audience :: Developers
Classifier: Intended Audience :: End Users/Desktop
Classifier: Programming Language :: Python :: 3
Classifier: Programming Language :: Python :: 3.10
Classifier: Programming Language :: Python :: 3.11
Classifier: Programming Language :: Python :: 3.12
Classifier: Topic :: Games/Entertainment :: Board Games
Requires-Python: >=3.10
License-File: LICENSE
Requires-Dist: chess
Requires-Dist: berserk
Requires-Dist: python-dotenv
Provides-Extra: docs
Requires-Dist: sphinx ; extra == 'docs'
Requires-Dist: myst-parser ; extra == 'docs'
Requires-Dist: furo ; extra == 'docs'
